cli_for_tools/__init__.py
cli_for_tools/paco_cli.py
cli_for_tools-0.3.0.dist-info/entry_points.txt
cli_for_tools-0.3.0.dist-info/licenses/LICENSE
cli_for_tools-0.3.0.dist-info/WHEEL
cli_for_tools-0.3.0.dist-info/METADATA
cli_for_tools-0.3.0.dist-info/RECORD
