Metadata-Version: 2.4
Name: cli_for_tools
Version: 0.3.0
Summary: Cli for traps team tools
Home-page: https://github.com/IslasGECI/cli_guadalupe_data
Author: Ciencia de Datos • GECI
Author-email: ciencia.datos@islas.org.mx
Requires-Python: >=3.9
Classifier: License :: OSI Approved :: GNU General Public License v3 or later (GPLv3+)
License-File: LICENSE
Requires-Dist: typer[all]
